e1jax/__init__.py
e1jax/_constants.py
e1jax/_model.py
e1jax/_tokenizer.py
e1jax/py.typed
e1jax-0.3.0.dist-info/licenses/LICENSE
e1jax-0.3.0.dist-info/METADATA
e1jax-0.3.0.dist-info/WHEEL
e1jax-0.3.0.dist-info/top_level.txt
e1jax-0.3.0.dist-info/RECORD
