Metadata-Version: 2.4
Name: e1jax
Version: 0.3.0
Summary: An implementation of the E1 protein language model family with Jax/Equinox.
Requires-Python: >=3.10
License-File: LICENSE
Requires-Dist: beartype>=0.22.8
Requires-Dist: einops>=0.8.1
Requires-Dist: equinox>=0.13.2
Requires-Dist: huggingface-hub<2.0,>=1.2.1
Requires-Dist: jax>=0.6.2
Requires-Dist: loguru>=0.7.3
Requires-Dist: safetensors>=0.7.0
Requires-Dist: tokenizers>=0.22.1
Requires-Dist: torch>=2.9.1
Dynamic: license-file
